hrpy/__init__.py
hrpy/__main__.py
hrpy/hr.py
hrpy-0.2.2.dist-info/entry_points.txt
hrpy-0.2.2.dist-info/LICENSE
hrpy-0.2.2.dist-info/WHEEL
hrpy-0.2.2.dist-info/METADATA
hrpy-0.2.2.dist-info/RECORD
